MatlabRumenjiaochengCYuyanBianchengWang/README.md
MatlabRumenjiaochengCYuyanBianchengWang/__init__.py
MatlabRumenjiaochengCYuyanBianchengWang/__main__.py
MatlabRumenjiaochengCYuyanBianchengWang/file.epub
MatlabRumenjiaochengCYuyanBianchengWang/index.html
MatlabRumenjiaochengCYuyanBianchengWang/css/__init__.py
MatlabRumenjiaochengCYuyanBianchengWang/css/annotations.css
MatlabRumenjiaochengCYuyanBianchengWang/css/main.css
MatlabRumenjiaochengCYuyanBianchengWang/css/normalize.css
MatlabRumenjiaochengCYuyanBianchengWang/css/popup.css
MatlabRumenjiaochengCYuyanBianchengWang/font/__init__.py
MatlabRumenjiaochengCYuyanBianchengWang/font/fontello.eot
MatlabRumenjiaochengCYuyanBianchengWang/font/fontello.svg
MatlabRumenjiaochengCYuyanBianchengWang/font/fontello.ttf
MatlabRumenjiaochengCYuyanBianchengWang/font/fontello.woff
MatlabRumenjiaochengCYuyanBianchengWang/img/__init__.py
MatlabRumenjiaochengCYuyanBianchengWang/img/annotator-glyph-sprite.png
MatlabRumenjiaochengCYuyanBianchengWang/img/annotator-icon-sprite.png
MatlabRumenjiaochengCYuyanBianchengWang/img/apple-touch-icon.png
MatlabRumenjiaochengCYuyanBianchengWang/img/cancelfullscreen.png
MatlabRumenjiaochengCYuyanBianchengWang/img/close.png
MatlabRumenjiaochengCYuyanBianchengWang/img/fullscreen.png
MatlabRumenjiaochengCYuyanBianchengWang/img/loader.gif
MatlabRumenjiaochengCYuyanBianchengWang/img/menu-icon.png
MatlabRumenjiaochengCYuyanBianchengWang/img/save.png
MatlabRumenjiaochengCYuyanBianchengWang/img/saved.png
MatlabRumenjiaochengCYuyanBianchengWang/img/settings-s.png
MatlabRumenjiaochengCYuyanBianchengWang/img/settings.png
MatlabRumenjiaochengCYuyanBianchengWang/img/star.png
MatlabRumenjiaochengCYuyanBianchengWang/js/__init__.py
MatlabRumenjiaochengCYuyanBianchengWang/js/epub.js
MatlabRumenjiaochengCYuyanBianchengWang/js/epub.min.js
MatlabRumenjiaochengCYuyanBianchengWang/js/epub.min.map
MatlabRumenjiaochengCYuyanBianchengWang/js/hooks.min.js
MatlabRumenjiaochengCYuyanBianchengWang/js/hooks.min.map
matlab_rumenjiaocheng_c_yuyan_biancheng_wang-2024.3.5.0.dist-info/METADATA
matlab_rumenjiaocheng_c_yuyan_biancheng_wang-2024.3.5.0.dist-info/WHEEL
matlab_rumenjiaocheng_c_yuyan_biancheng_wang-2024.3.5.0.dist-info/entry_points.txt
matlab_rumenjiaocheng_c_yuyan_biancheng_wang-2024.3.5.0.dist-info/top_level.txt
matlab_rumenjiaocheng_c_yuyan_biancheng_wang-2024.3.5.0.dist-info/RECORD
